__init__.py
openlibraryapi.py
openlibraryapi_peterinjapan1-0.1.0.dist-info/LICENSE.txt
openlibraryapi_peterinjapan1-0.1.0.dist-info/METADATA
openlibraryapi_peterinjapan1-0.1.0.dist-info/WHEEL
openlibraryapi_peterinjapan1-0.1.0.dist-info/top_level.txt
openlibraryapi_peterinjapan1-0.1.0.dist-info/RECORD
