Metadata-Version: 2.1
Name: openlibraryapi_peterinjapan1
Version: 0.1.0
Summary: A Python library for interacting with the Open Library API
Project-URL: Homepage, https://github.com/murraypdj/openlibraryapi_py
Project-URL: Issues, https://github.com/murraypdj/openlibraryapi_py/issues
Requires-Python: >=3.8
License-File: LICENSE.txt
